./LICENSE
./PKG-INFO
./README.md
./migrate.py
./pyproject.toml
./requirements.txt
./venv/lib/python3.12/site-packages/markdown_it_py-3.0.0.dist-info/LICENSE
./venv/lib/python3.12/site-packages/mdurl-0.1.2.dist-info/LICENSE
./venv/lib/python3.12/site-packages/pygments-2.19.1.dist-info/licenses/LICENSE
./venv/lib/python3.12/site-packages/rich-13.9.4.dist-info/LICENSE
./venv/lib/python3.12/site-packages/typing_extensions-4.12.2.dist-info/LICENSE
open_webui_postgres_migration-1.0.4.dist-info/METADATA
open_webui_postgres_migration-1.0.4.dist-info/WHEEL
open_webui_postgres_migration-1.0.4.dist-info/entry_points.txt
open_webui_postgres_migration-1.0.4.dist-info/licenses/LICENSE
open_webui_postgres_migration-1.0.4.dist-info/RECORD
