Metadata-Version: 2.4
Name: open-webui-postgres-migration
Version: 1.0.4
Summary: A robust, interactive tool for migrating Open WebUI databases from SQLite to PostgreSQL
Project-URL: Homepage, https://github.com/taylorwilsdon/open-webui-postgres-migration
Project-URL: Repository, https://github.com/taylorwilsdon/open-webui-postgres-migration
Project-URL: Issues, https://github.com/taylorwilsdon/open-webui-postgres-migration/issues
Author-email: Taylor Wilsdon <taylor@example.com>
License: MIT License
License-File: LICENSE
Keywords: database,migration,open-webui,postgresql,sqlite
Classifier: Development Status :: 5 - Production/Stable
Classifier: Intended Audience :: Developers
Classifier: Intended Audience :: System Administrators
Classifier: License :: OSI Approved :: MIT License
Classifier: Programming Language :: Python :: 3
Classifier: Programming Language :: Python :: 3.8
Classifier: Programming Language :: Python :: 3.9
Classifier: Programming Language :: Python :: 3.10
Classifier: Programming Language :: Python :: 3.11
Classifier: Programming Language :: Python :: 3.12
Classifier: Topic :: Database
Classifier: Topic :: Database :: Database Engines/Servers
Classifier: Topic :: Software Development :: Libraries :: Python Modules
Classifier: Topic :: System :: Systems Administration
Requires-Python: >=3.8.1
Requires-Dist: markdown-it-py==3.0.0
Requires-Dist: mdurl==0.1.2
Requires-Dist: psycopg[binary]==3.2.3
Requires-Dist: pygments==2.19.1
Requires-Dist: rich==13.9.4
Requires-Dist: typing-extensions==4.12.2
